chatollama/__init__.py
chatollama-0.2.13.dist-info/LICENSE
chatollama-0.2.13.dist-info/METADATA
chatollama-0.2.13.dist-info/WHEEL
chatollama-0.2.13.dist-info/top_level.txt
chatollama-0.2.13.dist-info/RECORD
