Metadata-Version: 2.1
Name: chatollama
Version: 0.2.13
Summary: A python module for conversational AI with ollama
Author: Matthew Sanchez
Author-email: xxspicymelonxx@gmail.com
Classifier: Programming Language :: Python :: 3
Classifier: License :: OSI Approved :: MIT License
Classifier: Operating System :: OS Independent
Requires-Python: >=3.10
License-File: LICENSE
Requires-Dist: ollama
Requires-Dist: asyncio
